hpa_menu/__init__.py
hpa_menu/parse.py
hpa_menu_scraper-0.2.2.dist-info/LICENSE
hpa_menu_scraper-0.2.2.dist-info/METADATA
hpa_menu_scraper-0.2.2.dist-info/WHEEL
hpa_menu_scraper-0.2.2.dist-info/top_level.txt
hpa_menu_scraper-0.2.2.dist-info/RECORD
